iocontrol/__init__.py
iocontrol/__main__.py
iocontrol/iocontrol.py
iocontrol/iocontrol.ui
iocontrol/pyqt5_style_rc.py
iocontrol/pyqt_style_rc.py
iocontrol/style.qss
iocontrol-1.0.dist-info/DESCRIPTION.rst
iocontrol-1.0.dist-info/METADATA
iocontrol-1.0.dist-info/RECORD
iocontrol-1.0.dist-info/WHEEL
iocontrol-1.0.dist-info/entry_points.txt
iocontrol-1.0.dist-info/metadata.json
iocontrol-1.0.dist-info/top_level.txt
