Metadata-Version: 2.0
Name: iocontrol
Version: 1.0
Summary: Graphical hardware perpheral access using MPIO
Home-page: UNKNOWN
Author: Joshua Henderson
Author-email: joshua.henderson@microchip.com
License: UNKNOWN
Platform: UNKNOWN
Classifier: Development Status :: 5 - Production/Stable
Classifier: Intended Audience :: Developers
Classifier: Intended Audience :: Education
Classifier: Intended Audience :: Information Technology
Classifier: License :: OSI Approved :: GNU General Public License v3 (GPLv3)
Classifier: Operating System :: POSIX
Classifier: Programming Language :: Python :: 2
Classifier: Programming Language :: Python :: 2.7
Classifier: Programming Language :: Python :: 3
Classifier: Topic :: Software Development :: Embedded Systems
Requires-Dist: mpio (>=1.0)
